kotano/__init__.py
kotano-1.0.4.dist-info/METADATA
kotano-1.0.4.dist-info/WHEEL
kotano-1.0.4.dist-info/top_level.txt
kotano-1.0.4.dist-info/RECORD
