Metadata-Version: 2.1
Name: kotano
Version: 1.0.4
Summary: Baby Hatano
Home-page: https://github.com/tripleko-llc/kotano
Author: Tripleko LLC
Author-email: jared@tripleko.com
License: UNKNOWN
Platform: UNKNOWN
Classifier: Programming Language :: Python :: 3
Classifier: License :: OSI Approved :: MIT License
Classifier: Operating System :: OS Independent
